{
  "date": "2024-10-23",
  "hsiLast": 20498,
  "steps": [
    {
      "from": 20600,
      "to": 20699,
      "type": "bear",
      "amount": 75
    },
    {
      "from": 20700,
      "to": 20799,
      "type": "bear",
      "amount": 48
    },
    {
      "from": 20800,
      "to": 20899,
      "type": "bear",
      "amount": 192
    },
    {
      "from": 20900,
      "to": 20999,
      "type": "bear",
      "amount": 256
    },
    {
      "from": 21000,
      "to": 21099,
      "type": "bear",
      "amount": 543
    },
    {
      "from": 21100,
      "to": 21199,
      "type": "bear",
      "amount": 510
    },
    {
      "from": 21200,
      "to": 21299,
      "type": "bear",
      "amount": 327
    },
    {
      "from": 21300,
      "to": 21399,
      "type": "bear",
      "amount": 234
    },
    {
      "from": 20300,
      "to": 20399,
      "type": "bull",
      "amount": 216
    },
    {
      "from": 20200,
      "to": 20299,
      "type": "bull",
      "amount": 154
    },
    {
      "from": 20100,
      "to": 20199,
      "type": "bull",
      "amount": 108
    },
    {
      "from": 20000,
      "to": 20099,
      "type": "bull",
      "amount": 309
    },
    {
      "from": 19900,
      "to": 19999,
      "type": "bull",
      "amount": 1140
    },
    {
      "from": 19800,
      "to": 19899,
      "type": "bull",
      "amount": 378
    },
    {
      "from": 19700,
      "to": 19799,
      "type": "bull",
      "amount": 216
    },
    {
      "from": 19600,
      "to": 19699,
      "type": "bull",
      "amount": 299
    }
  ]
}